gammagl/__init__.py
gammagl/lazy_load_paddle.py
gammagl/typing.py
gammagl/data/EdgeIndex.py
gammagl/data/__init__.py
gammagl/data/batch.py
gammagl/data/collate.py
gammagl/data/dataset.py
gammagl/data/download.py
gammagl/data/extract.py
gammagl/data/ggl_config_default.json
gammagl/data/graph.py
gammagl/data/heterograph.py
gammagl/data/in_memory_dataset.py
gammagl/data/makedirs.py
gammagl/data/separate.py
gammagl/data/storage.py
gammagl/data/utils.py
gammagl/data/view.py
gammagl/datasets/__init__.py
gammagl/datasets/alircd.py
gammagl/datasets/amazon.py
gammagl/datasets/aminer.py
gammagl/datasets/blogcatalog.py
gammagl/datasets/ca_grqc.py
gammagl/datasets/coauthor.py
gammagl/datasets/dblp.py
gammagl/datasets/entities.py
gammagl/datasets/flickr.py
gammagl/datasets/hgb.py
gammagl/datasets/imdb.py
gammagl/datasets/ml.py
gammagl/datasets/modelnet40.py
gammagl/datasets/molecule_net.py
gammagl/datasets/planetoid.py
gammagl/datasets/polblogs.py
gammagl/datasets/ppi.py
gammagl/datasets/reddit.py
gammagl/datasets/shapenet.py
gammagl/datasets/tu_dataset.py
gammagl/datasets/webkb.py
gammagl/datasets/wikics.py
gammagl/datasets/wikipedia_network.py
gammagl/datasets/zinc.py
gammagl/gglspeedup/__init__.py
gammagl/gglspeedup/gpufeature.py
gammagl/gglspeedup/gpusample.py
gammagl/gglspeedup/multifeat.py
gammagl/gglspeedup/multigpusample.py
gammagl/gglspeedup/sharedfeat.py
gammagl/gglspeedup/utils.py
gammagl/gglspeedup/cupy_and_thrust_code/__init__.py
gammagl/gglspeedup/cupy_and_thrust_code/kernels.py
gammagl/io/__init__.py
gammagl/io/npz.py
gammagl/io/planetiod.py
gammagl/io/tu.py
gammagl/io/txt_array.py
gammagl/layers/__init__.py
gammagl/layers/attention/__init__.py
gammagl/layers/attention/centrality_encoder.py
gammagl/layers/attention/edge_encoder.py
gammagl/layers/attention/graphormer_layer.py
gammagl/layers/attention/spatial_encoder.py
gammagl/layers/conv/JumpingKnowledge.py
gammagl/layers/conv/__init__.py
gammagl/layers/conv/agnn_conv.py
gammagl/layers/conv/appnp_conv.py
gammagl-0.4.0+pt21cpu.dist-info/LICENSE
gammagl-0.4.0+pt21cpu.dist-info/METADATA
gammagl-0.4.0+pt21cpu.dist-info/WHEEL
gammagl-0.4.0+pt21cpu.dist-info/top_level.txt
gammagl-0.4.0+pt21cpu.dist-info/RECORD
